gsea_incontext_notk/__init__.py
gsea_incontext_notk/__main__.py
gsea_incontext_notk/algorithm.py
gsea_incontext_notk/beta_binomial.py
gsea_incontext_notk/enrichr.py
gsea_incontext_notk/gsea.py
gsea_incontext_notk/parser.py
gsea_incontext_notk/utils.py
gsea_incontext_notk-0.1.3.dist-info/LICENSE.txt
gsea_incontext_notk-0.1.3.dist-info/METADATA
gsea_incontext_notk-0.1.3.dist-info/WHEEL
gsea_incontext_notk-0.1.3.dist-info/entry_points.txt
gsea_incontext_notk-0.1.3.dist-info/top_level.txt
gsea_incontext_notk-0.1.3.dist-info/RECORD
